antonLib/__init__.py
antonLib/__main__.py
antonLib/antonLib.py
antonLib/avatarInfo.py
antonLib/createdUser.py
antonLib/defAvatar.json
antonLib/exceptions.py
antonLib/pixelPaintInfo.py
antonLib/session.py
antonLib-0.1.1.3.2.dist-info/LICENSE
antonLib-0.1.1.3.2.dist-info/METADATA
antonLib-0.1.1.3.2.dist-info/WHEEL
antonLib-0.1.1.3.2.dist-info/entry_points.txt
antonLib-0.1.1.3.2.dist-info/top_level.txt
antonLib-0.1.1.3.2.dist-info/RECORD
