Metadata-Version: 2.1
Name: antonLib
Version: 0.1.1.3.2
Summary: A library for interacting with the learning platform anton.app.
Author: Antonabi
License: MIT License
Project-URL: repository, https://github.com/Antonabi/antonLib/
Project-URL: documentation, https://github.com/Antonabi/antonLib/blob/main/documentation/start.md
Keywords: antonapp,anton.app,anton
Classifier: License :: OSI Approved :: MIT License
Classifier: Programming Language :: Python
Classifier: Programming Language :: Python :: 3
Requires-Python: >=3.7
License-File: LICENSE
Requires-Dist: certifi
Requires-Dist: charset-normalizer
Requires-Dist: idna
Requires-Dist: requests
Requires-Dist: urllib3
Provides-Extra: build
Requires-Dist: build ; extra == 'build'
Requires-Dist: twine ; extra == 'build'
Provides-Extra: dev
Requires-Dist: black ; extra == 'dev'
Requires-Dist: bumpver ; extra == 'dev'
Requires-Dist: isort ; extra == 'dev'
Requires-Dist: mypy ; extra == 'dev'
Requires-Dist: pytest ; extra == 'dev'
